{"prefix": "fr-icon-", "version": "v1.13.0", "icons": ["capsule-fill", "capsule-line", "dislike-fill", "dislike-line", "dossier-fill", "dossier-line", "first-aid-kit-fill", "first-aid-kit-line", "hand-sanitizer-fill", "hand-sanitizer-line", "health-book-fill", "health-book-line", "heart-fill", "heart-line", "heart-pulse-fill", "heart-pulse-line", "lungs-fill", "lungs-line", "medicine-bottle-fill", "medicine-bottle-line", "mental-health-fill", "mental-health-line", "microscope-fill", "microscope-line", "psychotherapy-fill", "psychotherapy-line", "pulse-line", "stethoscope-fill", "stethoscope-line", "surgical-mask-fill", "surgical-mask-line", "syringe-fill", "syringe-line", "test-tube-fill", "test-tube-line", "thermometer-fill", "thermometer-line", "virus-fill", "virus-line"], "icon-style": "dsfr-health", "list-label": "DSFR Health"}
